{
  "Records": [
    {
      "eventID": "1",
      "eventName": "INSERT",
      "eventVersion": "1.0",
      "eventSource": "aws:dynamodb",
      "awsRegion": "us-east-1",
      "dynamodb": {
        "ApproximateCreationDateTime": 1647592120,
        "Keys": {
          "identifier": {
            "S": "test-user"
          }
        },
        "NewImage": {
          "identifier": {
            "S": "test-user"
          },
          "subscriptionTier": {
            "S": "BASIC"
          }
        },
        "SequenceNumber": "111",
        "SizeBytes": 26,
        "StreamViewType": "NEW_IMAGE"
      },
      "eventSourceARN": "arn:aws:dynamodb:us-east-1:123456789012:table/my-table/stream/2022-03-17T00:00:00.000"
    }
  ]
}
