{
  "name": "QuestionsAndAnswers",
  "locale": "en-US",
  "data": [
  {
    "intent": "question.age",
    "utterances": [
      "Are you at least 18 years of age or older?"
    ],
    "answers": []
  },
  {
    "intent": "question.citizenship",
    "utterances": [
      "Are you authorized to work in the United States",
      "Are you legally eligible to work in the United States?",
      "Do you have the right to work in the US",
      "What is your citizenship",
      "Are you a US Citizen (naturalized or U.S. Born)",
      "Because this supports the Federal Government, are you a US Citizen"
    ],
    "answers": []
  },
  {
    "intent": "question.city",
    "utterances": [
      "city"
    ],
    "answers": []
  },
  {
    "intent": "question.clearance",
    "utterances": [
      "Are you able to obtain and maintain a security clearance?"
    ],
    "answers": []
  },
  {
    "intent": "question.contact",
    "utterances": [
      "Please indicate if you agree to be contacted by sms text",
      "Yes, I agree to be contacted by text messages",
      "I consent to the hiring team of this job contacting me via text message",
      "What is your preferred method of contact?"
    ],
    "answers": []
  },
  {
    "intent": "question.education",
    "utterances": [
      "Highest Education Level, if a degree please list your degree type and major?",
      "Do you have a bachelor's degree?",
      "What is the highest education you have completed?",
      "Please choose the statement that best describes your education"
    ],
    "answers": []
  },
  {
    "intent": "question.english",
    "utterances": [
      "Do you speak Fluent English?"
    ],
    "answers": []
  },
  {
    "intent": "question.name",
    "utterances": [
      "Full Name",
      "Signature"
    ],
    "answers": [
      "Mitchell Blake"
    ]
  },
  {
    "intent": "question.notice",
    "utterances": [
      "If you’re currently working, how much notice do you need to give to your employer?"
    ],
    "answers": []
  },
  {
    "intent": "question.race",
    "utterances": [
      "race/ethnicity",
      "race or ethnicity",
      "Ethnic Background"
    ],
    "answers": [
      "Black or African American"
    ]
  },
  {
    "intent": "question.salary",
    "utterances": [
      "Salary requirements",
      "compensation",
      "Desired Pay",
      "Desired Annual Salary"
    ],
    "answers": [
      "120000"
    ]
  },
  {
    "intent": "question.streetAddress",
    "utterances": [
      "home address"
    ],
    "answers": []
  },
  {
    "intent": "question.vaccine",
    "utterances": [
      "Are you vaccinated?"
    ],
    "answers": []
  },
  {
    "intent": "question.zipAddress",
    "utterances": [
      "zip/postal code"
    ],
    "answers": []
  }]
}